lexorank/__init__.py
lexorank4py-0.1.0.dist-info/licenses/LICENSE
lexorank4py-0.1.0.dist-info/METADATA
lexorank4py-0.1.0.dist-info/WHEEL
lexorank4py-0.1.0.dist-info/top_level.txt
lexorank4py-0.1.0.dist-info/RECORD
