Metadata-Version: 2.4
Name: lexorank4py
Version: 0.1.0
Summary: LexoRank reference implementation in Python
Author-email: Luo Fan <luofan036@gmail.com>
License: MIT License
Project-URL: Homepage, https://github.com/luofanlf/lexorank4py
Project-URL: Repository, https://github.com/luofanlf/lexorank4py
Project-URL: Issues, https://github.com/luofanlf/lexorank4py/issues
Keywords: lexorank,ordering,ranking,base36
Classifier: Development Status :: 3 - Alpha
Classifier: Intended Audience :: Developers
Classifier: License :: OSI Approved :: MIT License
Classifier: Programming Language :: Python :: 3
Classifier: Programming Language :: Python :: 3.7
Classifier: Programming Language :: Python :: 3.8
Classifier: Programming Language :: Python :: 3.9
Classifier: Programming Language :: Python :: 3.10
Classifier: Programming Language :: Python :: 3.11
Requires-Python: >=3.7
License-File: LICENSE
Dynamic: license-file
